pixel_font_knife/__init__.py
pixel_font_knife/fs_util.py
pixel_font_knife/glyph_file_util.py
pixel_font_knife/glyph_mapping_util.py
pixel_font_knife/kerning_util.py
pixel_font_knife/mono_bitmap.py
pixel_font_knife-0.0.21.dist-info/WHEEL
pixel_font_knife-0.0.21.dist-info/METADATA
pixel_font_knife-0.0.21.dist-info/RECORD
