Metadata-Version: 2.4
Name: pixel-font-knife
Version: 0.0.21
Summary: A set of pixel font utilities
Keywords: font,pixel
Author: TakWolf
License-Expression: MIT
Classifier: Programming Language :: Python :: 3
Classifier: Programming Language :: Python :: 3.12
Classifier: Programming Language :: Python :: 3.13
Classifier: Programming Language :: Python :: 3.14
Classifier: License :: OSI Approved :: MIT License
Classifier: Operating System :: OS Independent
Requires-Dist: pypng>=0.20220715.0
Requires-Dist: unidata-blocks>=0.0.24
Requires-Dist: pyyaml>=6.0.3
Maintainer: TakWolf
Requires-Python: >=3.12
Project-URL: Homepage, https://github.com/TakWolf/pixel-font-knife
Project-URL: Issues, https://github.com/TakWolf/pixel-font-knife/issues
Project-URL: Source, https://github.com/TakWolf/pixel-font-knife
